DictionaryAPI-0.1.0.data/scripts/dictionaryapi.py
dictionaryapi/__init__.py
dictionaryapi/__main__.py
dictionaryapi/app.py
dictionaryapi/exception.py
DictionaryAPI-0.1.0.dist-info/LICENSE
DictionaryAPI-0.1.0.dist-info/METADATA
DictionaryAPI-0.1.0.dist-info/WHEEL
DictionaryAPI-0.1.0.dist-info/entry_points.txt
DictionaryAPI-0.1.0.dist-info/top_level.txt
DictionaryAPI-0.1.0.dist-info/RECORD
